{
 "updated": "2026-07-03T12:27:24+09:00",
 "kospi": {
  "price": 7767.38,
  "ma200": 5405.31,
  "ma50": 7851.17,
  "above_ma200": true,
  "above_ma50": false,
  "ma50_declining": false,
  "exit_signal": false,
  "entry_allowed": true,
  "updated": "2026-07-03T12:27:24+09:00"
 },
 "holdings": [
  {
   "ticker": "161890",
   "name": "한국콜마",
   "sector": "기타 화학제품 제조업",
   "entry_date": "2026-07-02",
   "entry_price": 113700.0,
   "entry_confidence": 95,
   "last_price": 115600.0,
   "peak_price": 115600.0,
   "return_pct": 1.67,
   "days_held": 1,
   "stage_now": 3,
   "confidence_now": 90,
   "last_updated": "2026-07-03",
   "signals_at_entry": [
    "MTT 통과",
    "전고점 돌파! 거래량 6.35x",
    "갭상승 동반",
    "MA 정배열"
   ]
  }
 ],
 "exited": [
  {
   "ticker": "041830",
   "name": "인바디",
   "sector": "의료용 기기 제조업",
   "entry_date": "2026-07-02",
   "entry_price": 58600.0,
   "entry_confidence": 95,
   "last_price": 53500.0,
   "peak_price": 58600.0,
   "return_pct": -8.7,
   "days_held": 1,
   "stage_now": 1,
   "confidence_now": 75,
   "last_updated": "2026-07-03",
   "signals_at_entry": [
    "MTT 통과",
    "RS 88 — 상위 강세",
    "전고점 돌파! 거래량 2.09x",
    "MA 정배열"
   ],
   "exit_date": "2026-07-03",
   "exit_price": 53500.0,
   "exit_reason": "손절 (-8%)"
  }
 ],
 "stats": {
  "holding_count": 1,
  "exited_count": 1,
  "avg_return": 1.67,
  "win_rate": 0.0
 }
}