{
  "updated": "2026-07-14T13:08:25+09:00",
  "base_date": "20260714",
  "dart": true,
  "criteria": {
    "min_cap": "시총 3,000억↑",
    "per_max": 15.0,
    "pbr_max": 1.5,
    "margin_min": 15.0,
    "fscore_min": 5,
    "fair_note": "적정가 = RIM(Ke 9%·ROE 상한 25%)·Graham 중 보수값"
  },
  "scanned": 350,
  "passed_value": 40,
  "candidates": [
    {
      "code": "015760",
      "name": "한국전력",
      "price": 33700,
      "mktcap": "216,342억",
      "per": 2.5,
      "pbr": 0.45,
      "div": null,
      "eps": 13311.0,
      "bps": 75035.0,
      "roe": 17.7,
      "fair": 147569,
      "fair_rim": 147569,
      "fair_graham": 149909,
      "margin": 77.2,
      "f_score": {
        "score": 7,
        "components": {
          "ROA>0": 1,
          "CFO>0": 0,
          "dROA>0": 1,
          "CFO>NI": 0,
          "dLev<0": 1,
          "dCurr>0": 1,
          "noNewShares": 1,
          "dMargin>0": 1,
          "dTurn>0": 1
        },
        "year": 2025
      },
      "high52": 69500,
      "low52": 33200,
      "pos52": 1,
      "trend": "down",
      "rsi14": 40.3,
      "off_high": -51.5
    },
    {
      "code": "073240",
      "name": "금호타이어",
      "price": 6400,
      "mktcap": "18,413억",
      "per": 5.3,
      "pbr": 0.91,
      "div": null,
      "eps": 1209.0,
      "bps": 7065.0,
      "roe": 17.1,
      "fair": 13424,
      "fair_rim": 13424,
      "fair_graham": 13863,
      "margin": 52.2,
      "f_score": {
        "score": 7,
        "components": {
          "ROA>0": 1,
          "CFO>0": 0,
          "dROA>0": 1,
          "CFO>NI": 0,
          "dLev<0": 1,
          "dCurr>0": 1,
          "noNewShares": 1,
          "dMargin>0": 1,
          "dTurn>0": 1
        },
        "year": 2025
      },
      "high52": 7840,
      "low52": 4220,
      "pos52": 60,
      "trend": "up",
      "rsi14": 63.8,
      "off_high": -18.4
    },
    {
      "code": "002380",
      "name": "KCC",
      "price": 422000,
      "mktcap": "36,090억",
      "per": 2.4,
      "pbr": 0.39,
      "div": null,
      "eps": 173128.0,
      "bps": 1063952.0,
      "roe": 16.3,
      "fair": 1926935,
      "fair_rim": 1926935,
      "fair_graham": 2035804,
      "margin": 78.2,
      "f_score": {
        "score": 5,
        "components": {
          "ROA>0": 1,
          "CFO>0": 0,
          "dROA>0": 1,
          "CFO>NI": 0,
          "dLev<0": 1,
          "dCurr>0": 0,
          "noNewShares": 1,
          "dMargin>0": 1,
          "dTurn>0": 0
        },
        "year": 2025
      },
      "high52": 692000,
      "low52": 367000,
      "pos52": 17,
      "trend": "down",
      "rsi14": 37.1,
      "off_high": -39.0
    },
    {
      "code": "375500",
      "name": "DL이앤씨",
      "price": 59500,
      "mktcap": "23,023억",
      "per": 6.9,
      "pbr": 0.47,
      "div": null,
      "eps": 8625.0,
      "bps": 126050.0,
      "roe": 6.8,
      "fair": 95238,
      "fair_rim": 95238,
      "fair_graham": 156402,
      "margin": 37.5,
      "f_score": {
        "score": 5,
        "components": {
          "ROA>0": 1,
          "CFO>0": 0,
          "dROA>0": 1,
          "CFO>NI": 0,
          "dLev<0": 1,
          "dCurr>0": 0,
          "noNewShares": 1,
          "dMargin>0": 1,
          "dTurn>0": 0
        },
        "year": 2025
      },
      "high52": 106600,
      "low52": 38450,
      "pos52": 31,
      "trend": "down",
      "rsi14": 46.2,
      "off_high": -44.2
    },
    {
      "code": "009970",
      "name": "영원무역홀딩스",
      "price": 194200,
      "mktcap": "25,143억",
      "per": 7.2,
      "pbr": 0.75,
      "div": null,
      "eps": 27133.0,
      "bps": 259821.0,
      "roe": 10.4,
      "fair": 300238,
      "fair_rim": 300238,
      "fair_graham": 398270,
      "margin": 35.4,
      "f_score": {
        "score": 5,
        "components": {
          "ROA>0": 1,
          "CFO>0": 1,
          "dROA>0": 1,
          "CFO>NI": 0,
          "dLev<0": 1,
          "dCurr>0": 0,
          "noNewShares": 1,
          "dMargin>0": 0,
          "dTurn>0": 0
        },
        "year": 2025
      },
      "high52": 262000,
      "low52": 129500,
      "pos52": 49,
      "trend": "flat",
      "rsi14": 70.6,
      "off_high": -25.9
    },
    {
      "code": "007340",
      "name": "DN오토모티브",
      "price": 37200,
      "mktcap": "21,766억",
      "per": 7.7,
      "pbr": 0.96,
      "div": null,
      "eps": 4809.0,
      "bps": 38780.0,
      "roe": 12.4,
      "fair": 53430,
      "fair_rim": 53430,
      "fair_graham": 64777,
      "margin": 30.4,
      "f_score": {
        "score": 5,
        "components": {
          "ROA>0": 1,
          "CFO>0": 0,
          "dROA>0": 0,
          "CFO>NI": 0,
          "dLev<0": 1,
          "dCurr>0": 0,
          "noNewShares": 1,
          "dMargin>0": 1,
          "dTurn>0": 1
        },
        "year": 2025
      },
      "high52": 54200,
      "low52": 21550,
      "pos52": 48,
      "trend": "flat",
      "rsi14": 46.6,
      "off_high": -31.4
    },
    {
      "code": "111770",
      "name": "영원무역",
      "price": 86300,
      "mktcap": "38,329억",
      "per": 7.8,
      "pbr": 0.9,
      "div": null,
      "eps": 11109.0,
      "bps": 96154.0,
      "roe": 11.6,
      "fair": 123932,
      "fair_rim": 123932,
      "fair_graham": 155029,
      "margin": 30.2,
      "f_score": {
        "score": 5,
        "components": {
          "ROA>0": 1,
          "CFO>0": 1,
          "dROA>0": 1,
          "CFO>NI": 0,
          "dLev<0": 1,
          "dCurr>0": 0,
          "noNewShares": 1,
          "dMargin>0": 0,
          "dTurn>0": 0
        },
        "year": 2025
      },
      "high52": 103200,
      "low52": 56800,
      "pos52": 64,
      "trend": "up",
      "rsi14": 70.7,
      "off_high": -16.4
    },
    {
      "code": "086280",
      "name": "현대글로비스",
      "price": 180000,
      "mktcap": "135,075억",
      "per": 7.8,
      "pbr": 1.3,
      "div": null,
      "eps": 23117.0,
      "bps": 138016.0,
      "roe": 16.7,
      "fair": 256096,
      "fair_rim": 256096,
      "fair_graham": 267930,
      "margin": 29.7,
      "f_score": {
        "score": 5,
        "components": {
          "ROA>0": 1,
          "CFO>0": 0,
          "dROA>0": 1,
          "CFO>NI": 0,
          "dLev<0": 0,
          "dCurr>0": 1,
          "noNewShares": 1,
          "dMargin>0": 1,
          "dTurn>0": 0
        },
        "year": 2025
      },
      "high52": 296000,
      "low52": 156100,
      "pos52": 17,
      "trend": "down",
      "rsi14": 43.7,
      "off_high": -39.2
    },
    {
      "code": "018670",
      "name": "SK가스",
      "price": 211500,
      "mktcap": "19,579억",
      "per": 8.3,
      "pbr": 0.65,
      "div": null,
      "eps": 25453.0,
      "bps": 325701.0,
      "roe": 7.8,
      "fair": 282274,
      "fair_rim": 282274,
      "fair_graham": 431887,
      "margin": 25.1,
      "f_score": {
        "score": 5,
        "components": {
          "ROA>0": 1,
          "CFO>0": 0,
          "dROA>0": 1,
          "CFO>NI": 0,
          "dLev<0": 0,
          "dCurr>0": 1,
          "noNewShares": 0,
          "dMargin>0": 1,
          "dTurn>0": 1
        },
        "year": 2025
      },
      "high52": 302000,
      "low52": 198600,
      "pos52": 12,
      "trend": "down",
      "rsi14": 53.3,
      "off_high": -30.0
    },
    {
      "code": "006730",
      "name": "서부T&D",
      "price": 10710,
      "mktcap": "6,884억",
      "per": 8.9,
      "pbr": 0.64,
      "div": null,
      "eps": 1206.0,
      "bps": 16666.0,
      "roe": 7.2,
      "fair": 13333,
      "fair_rim": 13333,
      "fair_graham": 21266,
      "margin": 19.7,
      "f_score": {
        "score": 5,
        "components": {
          "ROA>0": 1,
          "CFO>0": 0,
          "dROA>0": 1,
          "CFO>NI": 0,
          "dLev<0": 1,
          "dCurr>0": 1,
          "noNewShares": 1,
          "dMargin>0": 0,
          "dTurn>0": 0
        },
        "year": 2025
      },
      "high52": 20450,
      "low52": 8450,
      "pos52": 19,
      "trend": "down",
      "rsi14": 59.1,
      "off_high": -47.6
    }
  ]
}